apit/__init__.py
apit/calc.py
tests/__init__.py
tests/test_calc.py
apit_lk-0.1.2.dist-info/METADATA
apit_lk-0.1.2.dist-info/WHEEL
apit_lk-0.1.2.dist-info/top_level.txt
apit_lk-0.1.2.dist-info/RECORD
