Metadata-Version: 2.4
Name: apit_lk
Version: 0.1.2
Summary: Sri lanka APIT Calculation python library
Author: Dinuth Perera
Author-email: pm@dinuth.me
License: MIT
Keywords: conversion
Classifier: Development Status :: 4 - Beta
Classifier: Intended Audience :: Developers
Classifier: License :: OSI Approved :: MIT License
Classifier: Programming Language :: Python :: 3
Dynamic: author
Dynamic: author-email
Dynamic: classifier
Dynamic: description
Dynamic: keywords
Dynamic: license
Dynamic: summary
